artelib/__init__.py
artelib/speak.py
artelib/web.py
artelib-1.0.0.dist-info/licenses/LICENSE
artelib-1.0.0.dist-info/METADATA
artelib-1.0.0.dist-info/WHEEL
artelib-1.0.0.dist-info/top_level.txt
artelib-1.0.0.dist-info/RECORD
